{"main": {"folder1": {"dog": {"pronuncation": "", "definition": ["\u0441\u043e\u0431\u0430\u043a\u0430"]}, "bye": {"pronuncation": "", "definition": ["\u043f\u043e\u043a\u0430"]}, "hello": {"pronuncation": "", "definition": ["\u043f\u0440\u0438\u0432\u0435\u0442"]}, "abaca": {"pronuncation": "[\u0251:b\u0251:`k\u0251:]", "definition": ["\u0430\u0431\u0430\u043a\u0430"]}, "aback": {"pronuncation": "[\u0259`b\u00e6k]", "definition": [" \u0441\u0437\u0430\u0434\u0438", " \u0437\u0430\u0434\u043e\u043c", "\u043d\u0430\u0437\u0430\u0434"]}, "sex": {"pronuncation": "", "definition": ["\u0441\u0435\u043a\u0441"]}}, "1": {}}}